dscyd/__init__.py
dscyd/django.py
dscyd-0.0.1.dist-info/METADATA
dscyd-0.0.1.dist-info/WHEEL
dscyd-0.0.1.dist-info/top_level.txt
dscyd-0.0.1.dist-info/RECORD
